CHANGES.rst
LICENCE.txt
MANIFEST.in
README.md
setup.cfg
setup.py
django_plugins.egg-info/PKG-INFO
django_plugins.egg-info/SOURCES.txt
django_plugins.egg-info/dependency_links.txt
django_plugins.egg-info/not-zip-safe
django_plugins.egg-info/requires.txt
django_plugins.egg-info/top_level.txt
djangoplugins/__init__.py
djangoplugins/admin.py
djangoplugins/fields.py
djangoplugins/models.py
djangoplugins/point.py
djangoplugins/tests.py
djangoplugins/utils.py
djangoplugins/views.py
djangoplugins/management/__init__.py
djangoplugins/management/commands/__init__.py
djangoplugins/management/commands/syncplugins.py
djangoplugins/templatetags/__init__.py
djangoplugins/templatetags/plugins.py