Metadata-Version: 1.1
Name: django-plugins
Version: 0.2.4
Summary: django-plugins.
Home-page: https://github.com/krischer/django-plugins
Author: Mantas Zimnickas
Author-email: sirexas@gmail.com
License: LGPL
Download-URL: http://pypi.python.org/pypi/django-plugins
Platform: UNKNOWN
Classifier: Development Status :: 5 - Production/Stable
Classifier: Environment :: Web Environment
Classifier: Framework :: Django
Classifier: Intended Audience :: Developers
Classifier: License :: OSI Approved :: GNU Library or Lesser General Public License (LGPL)
Classifier: Operating System :: OS Independent
Classifier: Programming Language :: Python
Classifier: Topic :: Software Development :: Libraries :: Python Modules
